ecoinvent_migrate/__init__.py
ecoinvent_migrate/data_io.py
ecoinvent_migrate/ei_release.py
ecoinvent_migrate/errors.py
ecoinvent_migrate/main.py
ecoinvent_migrate/patches.py
ecoinvent_migrate/utils.py
ecoinvent_migrate/wrangling.py
ecoinvent_migrate-0.6.2.dist-info/licenses/LICENSE
ecoinvent_migrate-0.6.2.dist-info/METADATA
ecoinvent_migrate-0.6.2.dist-info/WHEEL
ecoinvent_migrate-0.6.2.dist-info/top_level.txt
ecoinvent_migrate-0.6.2.dist-info/RECORD
