Metadata-Version: 2.4
Name: ecoinvent_migrate
Version: 0.6.2
Summary: Code to generate Randonneur migration files for ecoinvent releases
Author-email: Chris Mutel <cmutel@gmail.com>
Maintainer-email: Chris Mutel <cmutel@gmail.com>
Project-URL: source, https://github.com/brightway-lca/ecoinvent_migrate
Project-URL: homepage, https://github.com/brightway-lca/ecoinvent_migrate
Project-URL: tracker, https://github.com/brightway-lca/ecoinvent_migrate/issues
Classifier: Development Status :: 4 - Beta
Classifier: Programming Language :: Python
Classifier: Programming Language :: Python :: 3
Classifier: Programming Language :: Python :: 3.9
Classifier: Programming Language :: Python :: 3.10
Classifier: Programming Language :: Python :: 3.11
Classifier: Programming Language :: Python :: 3.12
Classifier: Natural Language :: English
Classifier: Operating System :: OS Independent
Classifier: Topic :: Scientific/Engineering
Requires-Python: >=3.10
License-File: LICENSE
Requires-Dist: ecoinvent_interface
Requires-Dist: loguru
Requires-Dist: pandas
Requires-Dist: platformdirs
Requires-Dist: randonneur
Requires-Dist: tqdm
Requires-Dist: xmltodict
Provides-Extra: testing
Requires-Dist: ecoinvent_migrate; extra == "testing"
Requires-Dist: pytest; extra == "testing"
Requires-Dist: pytest-cov; extra == "testing"
Requires-Dist: pytest-loguru; extra == "testing"
Requires-Dist: python-coveralls; extra == "testing"
Provides-Extra: dev
Requires-Dist: build; extra == "dev"
Requires-Dist: pre-commit; extra == "dev"
Requires-Dist: pylint; extra == "dev"
Requires-Dist: pytest; extra == "dev"
Requires-Dist: pytest-cov; extra == "dev"
Requires-Dist: pytest-loguru; extra == "dev"
Requires-Dist: pytest-randomly; extra == "dev"
Requires-Dist: setuptools; extra == "dev"
Dynamic: license-file
